data_mat.sv
//implement the data structure for the AES stast matrix, which is a 4x4 matrix of bytes
module data_mat (
    input wire clk,
    input wire reset_n,
    input wire [31:0] col_in,
    input wire [1:0] input_idx, //index for either row or column
    input wire input_row_col, //0 for row, 1 for column
    input wire write_enable, //enable signal for writing
    input wire [1:0] output_idx, //index for either row or column
    input wire output_row_col, //0 for row, 1 for column
    output reg [31:0] out //reg to hold output data until next read 
);

    //internal 4x4 matrix of bytes, represented as a 2D array
    reg [7:0] state [0:3][0:3];
    assign debug_state = {state[0][0], state[0][1], state[0][2], state[0][3],
                          state[1][0], state[1][1], state[1][2], state[1][3],
                          state[2][0], state[2][1], state[2][2], state[2][3],
                          state[3][0], state[3][1], state[3][2], state[3][3]};

    //synchronous write operation
    always @(posedge clk or negedge reset_n) begin
        if (!reset_n) begin
            integer i, j;
            for (i = 0; i < 4; i = i + 1)
                for (j = 0; j < 4; j = j + 1)
                    state[i][j] <= 8'b0;
        end else if (write_enable) begin
            if (input_row_col) begin
                // Writing to a column
                state[0][input_idx] <= col_in[31:24];
                state[1][input_idx] <= col_in[23:16];
                state[2][input_idx] <= col_in[15:8];
                state[3][input_idx] <= col_in[7:0];
            end else begin
                // Writing to a row
                state[input_idx][0] <= col_in[31:24];
                state[input_idx][1] <= col_in[23:16];
                state[input_idx][2] <= col_in[15:8];
                state[input_idx][3] <= col_in[7:0];
            end
        end
    end

    //combinational read operation
    always @(*) begin
        if (output_row_col) begin
            // Reading a column
            out = {state[0][output_idx], state[1][output_idx], state[2][output_idx], state[3][output_idx]};
        end else begin
            // Reading a row
            out = {state[output_idx][0], state[output_idx][1], state[output_idx][2], state[output_idx][3]};
        end
    end


endmodule

data_mat_tb.sv
//test the data matrix module

`timescale 1ns/1ps

module data_mat_tb();
    reg clk;
    reg [1:0] input_idx;
    reg input_row_col;
    reg [1:0] output_idx;
    reg output_row_col;
    reg write_enable;
    reg [31:0] col_in;
    wire [31:0] out;
    wire [127:0] debug_state;
    reg reset_n;

    // Instantiate the DUT
    data_mat dut (
        .clk(clk),
        .reset_n(reset_n),
        .col_in(col_in),
        .input_idx(input_idx),
        .input_row_col(input_row_col),
        .write_enable(write_enable),
        .output_idx(output_idx),
        .output_row_col(output_row_col),
        .out(out)
    );

    initial clk = 0;
    always #5 clk = ~clk;

    //vcddump
    initial begin
        $dumpfile("data_mat_tb.vcd");
        $dumpvars(0, data_mat_tb);
    end

    initial begin
        reset_n = 0;
        col_in = 0;
        input_idx = 0;
        input_row_col = 0;
        write_enable = 0;
        output_idx = 0;
        output_row_col = 0;
        #20;
        reset_n = 1;
        #10;
        //write to row 0 
        col_in = 32'h00112233;
        input_idx = 0;
        input_row_col = 0; //row
        write_enable = 1;
        #10;
        write_enable = 0;
        #10;
        //read row 0
        output_idx = 0;
        output_row_col = 0; //row
        #10;
        if (out !== 32'h00112233) $display("Test 1 Failed: Expected 0x00112233, got %h", out);
        else $display("Test 1 Passed");
        #10;
        //write to column 1
        col_in = 32'h44556677;
        input_idx = 1;
        input_row_col = 1; //column
        write_enable = 1;
        #10;
        write_enable = 0;
        #10;
        //read column 1
        output_idx = 1;
        output_row_col = 1; //column
        #10;
        if (out !== 32'h44556677) $display("Test 2 Failed: Expected 0x44556677, got %h", out);
        else $display("Test 2 Passed");
        #10;
        //read row 0 again to ensure it is unchanged (save for the first byte, which was modified by the
        //write to row 1!)
        output_idx = 0;
        output_row_col = 0; //row
        #10;
        if (out !== 32'h00442233) $display("Test 3 Failed: Expected 0x00112233, got %h", out);
        else $display("Test 3 Passed");
        #10;
        $finish;
    end
endmodule

data_mat_tb.vcd
$date
	Thu Sep 18 14:25:42 2025
$end
$version
	Icarus Verilog
$end
$timescale
	1ps
$end
$scope module data_mat_tb $end
$var wire 32 ! out [31:0] $end
$var reg 1 " clk $end
$var reg 32 # col_in [31:0] $end
$var reg 2 $ input_idx [1:0] $end
$var reg 1 % input_row_col $end
$var reg 2 & output_idx [1:0] $end
$var reg 1 ' output_row_col $end
$var reg 1 ( reset_n $end
$var reg 1 ) write_enable $end
$scope module dut $end
$var wire 1 " clk $end
$var wire 32 * col_in [31:0] $end
$var wire 2 + input_idx [1:0] $end
$var wire 1 % input_row_col $end
$var wire 2 , output_idx [1:0] $end
$var wire 1 ' output_row_col $end
$var wire 1 ( reset_n $end
$var wire 1 ) write_enable $end
$var wire 1 - debug_state $end
$var reg 32 . out [31:0] $end
$scope begin $unm_blk_2 $end
$var integer 32 / i [31:0] $end
$var integer 32 0 j [31:0] $end
$upscope $end
$upscope $end
$upscope $end
$enddefinitions $end
$comment Show the parameter values. $end
$dumpall
$end
#0
$dumpvars
b100 0
b100 /
b0 .
0-
b0 ,
b0 +
b0 *
0)
0(
0'
b0 &
0%
b0 $
b0 #
0"
b0 !
$end
#5000
b100 0
b100 /
1"
#10000
0"
#15000
b100 0
b100 /
1"
#20000
0"
1(
#25000
1"
#30000
0"
1)
b100010010001000110011 #
b100010010001000110011 *
#35000
b100010010001000110011 !
b100010010001000110011 .
1"
#40000
0"
0)
#45000
1"
#50000
0"
#55000
1"
#60000
0"
#65000
1"
#70000
0"
1)
1%
b1 $
b1 +
b1000100010101010110011001110111 #
b1000100010101010110011001110111 *
#75000
b10001000010001000110011 !
b10001000010001000110011 .
1"
#80000
0"
0)
#85000
1"
#90000
b1000100010101010110011001110111 !
b1000100010101010110011001110111 .
0"
1'
b1 &
b1 ,
#95000
1"
#100000
0"
#105000
1"
#110000
b10001000010001000110011 !
b10001000010001000110011 .
0"
0'
b0 &
b0 ,
