state_manager.sv
module state_manager (
    input wire clock,
    input wire reset_n,
    input wire start_write_n, //active low start signal for writing the state matrix and key 
    input wire start_read_n, //active low start signal for reading the ciphertext output
    input wire key_expand_done, //signal from key expansion module indicating that round keys are ready
    output reg done,
    output reg [5:0] dbg_state, //debugging output to monitor current state
    output reg [3:0] dbg_round, //debugging output to monitor current round
    output reg [3:0] matrix_in_sel,
    output reg matrix_write_enable,
    output reg input_mat_row_col, //0 for row, 1 for column
    output reg [1:0] input_mat_idx, //2 bit index for row/column
    output reg output_mat_row_col, //0 for row, 1 for column
    output reg [1:0] output_mat_idx, //2 bit index for row/column
    output reg key_start, //signal to start key expansion
    output reg [1:0] count_4_out //2-bit output for monitoring count_4
);
//finite state machine for managing the state of the AES encryption/decryption process


//define states
localparam IDLE = 6'd0;
localparam PTEXT_WRITE = 6'd1;
localparam KEY_WRITE = 6'd2;
localparam COMPUTE_ROUNDKEYS = 6'd3;
localparam SUBBYTES = 6'd4;
localparam SHIFTROWS = 6'd5;
localparam MIXCOLUMNS = 6'd6;
localparam ADDROUNDKEY = 6'd7;
localparam ENCRYPTION_DONE = 6'd8;
localparam CTEXT_READ = 6'd9;
localparam INIT_ADDROUNDKEY = 6'd10;

reg [5:0] current_state, next_state;
reg [3:0] round_counter, next_round_counter; //4-bit counter for 10 rounds
reg [1:0] count_4, next_count_4; //2-bit counter for 4 rows/columns

assign count_4_out = count_4;

// State register
always @(posedge clock or negedge reset_n) begin
    if (!reset_n) begin
        current_state <= IDLE;
        round_counter <= 4'd0;
        count_4 <= 2'd0;
        done <= 1'b0;
    end else begin
        current_state <= next_state;
        round_counter <= next_round_counter;
        count_4 <= next_count_4;
    end
end

// Next state logic
always @(*) begin
    next_state = current_state;
    next_round_counter = round_counter;
    next_count_4 = count_4;
    case (current_state)
        IDLE: begin
            if (!start_write_n) begin
                next_state = PTEXT_WRITE;
                next_count_4 = 2'd0;
            end
        end
        PTEXT_WRITE: begin
            if (count_4 == 2'd3) begin
                next_state = KEY_WRITE;
                next_count_4 = 2'd0;
            end else begin
                next_count_4 = count_4 + 1;
            end
        end
        KEY_WRITE: begin
            if (count_4 == 2'd3) begin
                next_state = INIT_ADDROUNDKEY;
                next_count_4 = 2'd0;
            end else begin
                next_count_4 = count_4 + 1;
            end
        end
        INIT_ADDROUNDKEY: begin
            if (count_4 == 2'd3) begin
                next_state = COMPUTE_ROUNDKEYS;
                next_count_4 = 2'd0;
            end else begin
                next_count_4 = count_4 +1;
            end
        end
        COMPUTE_ROUNDKEYS: begin
            if (key_expand_done) begin
                next_state = SUBBYTES;
                next_round_counter = 4'd0;
                next_count_4 = 2'd0;
            end
        end
        SUBBYTES: begin
            if (count_4 == 2'd3) begin
                next_state = SHIFTROWS;
                next_count_4 = 2'd0;
            end else begin
                next_count_4 = count_4 + 1;
            end
        end
        SHIFTROWS: begin
            if (count_4 == 2'd3) begin
                //on the last round, skip MixColumns
                if (round_counter == 4'd9) begin
                    next_state = ADDROUNDKEY;
                end else
                next_state = MIXCOLUMNS;
                next_count_4 = 2'd0;
            end else begin
                next_count_4 = count_4 + 1;
            end
        end
        MIXCOLUMNS: begin
            if (count_4 == 2'd3) begin
                next_state = ADDROUNDKEY;
                next_count_4 = 2'd0;
            end else begin
                next_count_4 = count_4 + 1;
            end
        end
        ADDROUNDKEY: begin
            //after AddRoundKey, either go to the next round or finish
            if (count_4 == 2'd3) begin
                if (round_counter == 4'd9) begin
                    next_state = ENCRYPTION_DONE;
                    next_count_4 = 2'd0;
                end else begin
                    next_state = SUBBYTES;
                    next_round_counter = round_counter + 1;
                    next_count_4 = 2'd0;
                end
            end else begin
                next_count_4 = count_4 + 1;
            end
        end
        ENCRYPTION_DONE: begin
            if (!start_read_n) begin
                next_state = CTEXT_READ;
                next_count_4 = 2'd0;
            end
        end
        CTEXT_READ: begin
            if (count_4 == 2'd3) begin
                next_state = IDLE;
                next_count_4 = 2'd0;
            end else begin
                next_count_4 = count_4 + 1;
            end
        end
        default: begin
            next_state = IDLE;
            next_count_4 = 2'd0;
            next_round_counter = 4'd0;
        end
    endcase
end

//combinational output logic based on current state
always @(*) begin
    // Default assignments
    input_mat_row_col = 1'b0;
    input_mat_idx = 2'd0;
    output_mat_row_col = 1'b0;
    output_mat_idx = 2'd0;
    done = 1'b0;
    case(current_state)
        IDLE: begin
            matrix_in_sel = 4'd0;
            matrix_write_enable = 1'b0;
            dbg_state = IDLE;
            dbg_round = round_counter;
            key_start = 1'b0;
        end
        PTEXT_WRITE: begin
            matrix_in_sel = 4'd0; //plaintext input
            matrix_write_enable = 1'b1;
            input_mat_row_col = 1'b1; //writing columns
            input_mat_idx = count_4;
            dbg_state = PTEXT_WRITE;
            dbg_round = round_counter;
            key_start = 1'b0;
        end
        KEY_WRITE: begin
            matrix_in_sel = 4'bxxxx; //don't care
            matrix_write_enable = 1'b0;
            input_mat_row_col = 1'b0; //writing rows
            input_mat_idx = count_4;
            dbg_state = KEY_WRITE;
            dbg_round = round_counter;
            key_start = count_4 == 2'd0 ? 1'b1 : 1'b0;
        end
        INIT_ADDROUNDKEY: begin
            matrix_in_sel = 4'd4; //AddRoundKey operation input
            matrix_write_enable = 1'b1;
            input_mat_row_col = 1'b1; //writing cols
            input_mat_idx = count_4;
            output_mat_row_col = 1'b1; //reading cols
            output_mat_idx = count_4;
            dbg_state = INIT_ADDROUNDKEY;
            dbg_round = 4'd0;
            key_start = 1'b0;
        end
        COMPUTE_ROUNDKEYS: begin
            matrix_in_sel = 4'bxxxx; //don't care
            matrix_write_enable = 1'b0;
            dbg_state = COMPUTE_ROUNDKEYS;
            dbg_round = round_counter;
            key_start = 1'b0;
        end
        SUBBYTES: begin
            matrix_in_sel = 4'd1; //SubBytes operation input
            matrix_write_enable = 1'b1;
            input_mat_row_col = 1'b0; //processing rows
            input_mat_idx = count_4;
            output_mat_row_col = 1'b0; //reading rows
            output_mat_idx = count_4;
            dbg_state = SUBBYTES;
            dbg_round = round_counter;
            key_start = 1'b0;
        end
        SHIFTROWS: begin
            matrix_in_sel = 4'd2; //ShiftRows operation input
            matrix_write_enable = 1'b1;
            input_mat_row_col = 1'b0; //processing rows
            input_mat_idx = count_4;    
            output_mat_row_col = 1'b0; //reading rows
            output_mat_idx = count_4;
            dbg_state = SHIFTROWS;
            dbg_round = round_counter;
            key_start = 1'b0;
        end
        MIXCOLUMNS: begin
            matrix_in_sel = 4'd3; //MixColumns operation input
            matrix_write_enable = 1'b1;
            input_mat_row_col = 1'b1; //processing columns
            input_mat_idx = count_4;
            output_mat_row_col = 1'b1; //reading columns
            output_mat_idx = count_4;
            dbg_state = MIXCOLUMNS;
            dbg_round = round_counter;
            key_start = 1'b0;
        end
        ADDROUNDKEY: begin
            matrix_in_sel = 4'd4; //AddRoundKey operation input
            matrix_write_enable = 1'b1;
            input_mat_row_col = 1'b1; //processing columns
            input_mat_idx = count_4;
            output_mat_row_col = 1'b1; //reading columns
            output_mat_idx = count_4;
            dbg_state = ADDROUNDKEY;
            dbg_round = round_counter;
            key_start = 1'b0;
        end
        ENCRYPTION_DONE: begin
            matrix_in_sel = 4'bxxxx; //don't care
            matrix_write_enable = 1'b0;
            dbg_state = ENCRYPTION_DONE;
            dbg_round = round_counter;
            key_start = 1'b0;
            done = (count_4 == 2'd0) ? 1'b1 : 1'b0;
        end
        CTEXT_READ: begin
            matrix_in_sel = 4'bxxxx; //don't care
            matrix_write_enable = 1'b0;
            output_mat_row_col = 1'b1; //reading columns
            output_mat_idx = count_4;
            dbg_state = CTEXT_READ;
            dbg_round = round_counter;
            key_start = 1'b0;
        end
        default: begin
            matrix_in_sel = 4'd0;
            matrix_write_enable = 1'b0;
            dbg_state = 6'bxxxxxx;
            dbg_round = 4'bxxxx;
            key_start = 1'b0;
            done = 1'b0;
        end
    endcase
end


endmodule

state_manager_tb.sv
`timescale 1ns / 1ps

module state_manager_tb;
    // Inputs
    reg clock;
    reg reset_n;
    reg start_write_n;
    reg start_read_n;
    reg key_expand_done;

    // Outputs
    wire [5:0] dbg_state;
    wire [3:0] dbg_round;
    wire [3:0] matrix_in_sel;
    wire matrix_write_enable;
    wire input_mat_row_col;
    wire [1:0] input_mat_idx;
    wire output_mat_row_col;
    wire [1:0] output_mat_idx;
    wire key_start;
    wire [1:0] count_4_out;

    // Instantiate the DUT
    state_manager dut (
        .clock(clock),
        .reset_n(reset_n),
        .start_write_n(start_write_n),
        .start_read_n(start_read_n),
        .key_expand_done(key_expand_done),
        .done(done),
        .dbg_state(dbg_state),
        .dbg_round(dbg_round),
        .matrix_in_sel(matrix_in_sel),
        .matrix_write_enable(matrix_write_enable),
        .input_mat_row_col(input_mat_row_col),
        .output_mat_row_col(output_mat_row_col),
        .output_mat_idx(output_mat_idx),
        .key_start(key_start),
        .count_4_out(count_4_out)
    );

    // Clock generation
    initial clock = 0;
    always #5 clock = ~clock;

    // VCD dump
    initial begin
        $dumpfile("state_manager_tb.vcd");
        $dumpvars(0, state_manager_tb);
    end

    // Stimulus
    initial begin
        // Initialize inputs
        reset_n = 0;
        start_write_n = 1;
        start_read_n = 1;
        key_expand_done = 0;
        #20;
        reset_n = 1;
        #10;

        // Start write (active low)
        start_write_n = 0;
        #10;
        start_write_n = 1;

        // Wait for PTEXT_WRITE and KEY_WRITE to finish
        repeat (10) @(posedge clock);

        // Simulate key expansion done
        key_expand_done = 1;
        @(posedge clock);
        key_expand_done = 0;

        // Wait for rounds to complete
        wait (done == 1);

        #10;
        // Start read (active low)
        start_read_n = 0;
        #10;
        start_read_n = 1;

        // Wait for CTEXT_READ and done
        repeat (10) @(posedge clock);

        $finish;
    end
endmodule

state_manager_tb.vcd
$date
	Thu Sep 18 15:29:56 2025
$end
$version
	Icarus Verilog
$end
$timescale
	1ps
$end
$scope module state_manager_tb $end
$var wire 1 ! output_mat_row_col $end
$var wire 2 " output_mat_idx [1:0] $end
$var wire 1 # matrix_write_enable $end
$var wire 4 $ matrix_in_sel [3:0] $end
$var wire 1 % key_start $end
$var wire 1 & input_mat_row_col $end
$var wire 1 ' done $end
$var wire 6 ( dbg_state [5:0] $end
$var wire 4 ) dbg_round [3:0] $end
$var wire 2 * count_4_out [1:0] $end
$var reg 1 + clock $end
$var reg 1 , key_expand_done $end
$var reg 1 - reset_n $end
$var reg 1 . start_read_n $end
$var reg 1 / start_write_n $end
$scope module dut $end
$var wire 1 + clock $end
$var wire 2 0 count_4_out [1:0] $end
$var wire 1 , key_expand_done $end
$var wire 1 - reset_n $end
$var wire 1 . start_read_n $end
$var wire 1 / start_write_n $end
$var parameter 6 1 ADDROUNDKEY $end
$var parameter 6 2 COMPUTE_ROUNDKEYS $end
$var parameter 6 3 CTEXT_READ $end
$var parameter 6 4 ENCRYPTION_DONE $end
$var parameter 6 5 IDLE $end
$var parameter 6 6 INIT_ADDROUNDKEY $end
$var parameter 6 7 KEY_WRITE $end
$var parameter 6 8 MIXCOLUMNS $end
$var parameter 6 9 PTEXT_WRITE $end
$var parameter 6 : SHIFTROWS $end
$var parameter 6 ; SUBBYTES $end
$var reg 2 < count_4 [1:0] $end
$var reg 6 = current_state [5:0] $end
$var reg 4 > dbg_round [3:0] $end
$var reg 6 ? dbg_state [5:0] $end
$var reg 1 ' done $end
$var reg 2 @ input_mat_idx [1:0] $end
$var reg 1 & input_mat_row_col $end
$var reg 1 % key_start $end
$var reg 4 A matrix_in_sel [3:0] $end
$var reg 1 # matrix_write_enable $end
$var reg 2 B next_count_4 [1:0] $end
$var reg 4 C next_round_counter [3:0] $end
$var reg 6 D next_state [5:0] $end
$var reg 2 E output_mat_idx [1:0] $end
$var reg 1 ! output_mat_row_col $end
$var reg 4 F round_counter [3:0] $end
$upscope $end
$upscope $end
$enddefinitions $end
$comment Show the parameter values. $end
$dumpall
b100 ;
b101 :
b1 9
b110 8
b10 7
b1010 6
b0 5
b1000 4
b1001 3
b11 2
b111 1
$end
#0
$dumpvars
b0 F
b0 E
b0 D
b0 C
b0 B
b0 A
b0 @
b0 ?
b0 >
b0 =
b0 <
b0 0
1/
1.
0-
0,
0+
b0 *
b0 )
b0 (
0'
0&
0%
b0 $
0#
b0 "
0!
$end
#5000
1+
#10000
0+
#15000
1+
#20000
0+
1-
#25000
1+
#30000
b1 D
0+
0/
#35000
b1 (
b1 ?
1#
b1 B
b1 =
1+
#40000
b1 B
0+
1/
#45000
b1 @
b10 B
b1 *
b1 0
b1 <
1+
#50000
0+
#55000
b10 @
b11 B
b10 *
b10 0
b10 <
1+
#60000
0+
#65000
b11 @
b0 B
b10 D
b11 *
b11 0
b11 <
1+
#70000
0+
#75000
1%
b10 (
b10 ?
0#
bx $
bx A
b0 @
b1 B
b0 *
b0 0
b0 <
b10 =
1+
#80000
0+
#85000
0%
b1 @
b10 B
b1 *
b1 0
b1 <
1+
#90000
0+
#95000
b10 @
b11 B
b10 *
b10 0
b10 <
1+
#100000
0+
#105000
b11 @
b0 B
b1010 D
b11 *
b11 0
b11 <
1+
#110000
0+
#115000
b1010 (
b1010 ?
1#
b100 $
b100 A
b0 @
b11 D
b0 *
b0 0
b0 <
b1010 =
1+
#120000
0+
#125000
b11 (
b11 ?
0#
bx $
bx A
b11 =
1+
#130000
0+
#135000
b100 D
1,
1+
#140000
0+
#145000
b100 (
b100 ?
1#
b1 $
b1 A
b1 B
b100 =
b100 D
0,
1+
#150000
0+
#155000
b1 "
b1 E
b1 @
b10 B
b1 *
b1 0
b1 <
1+
#160000
0+
#165000
b10 "
b10 E
b10 @
b11 B
b10 *
b10 0
b10 <
1+
#170000
0+
#175000
b11 "
b11 E
b11 @
b0 B
b101 D
b11 *
b11 0
b11 <
1+
#180000
0+
#185000
b101 (
b101 ?
b10 $
b10 A
b0 "
b0 E
b0 @
b1 B
b0 *
b0 0
b0 <
b101 =
1+
#190000
0+
#195000
b1 "
b1 E
b1 @
b10 B
b1 *
b1 0
b1 <
1+
#200000
0+
#205000
b10 "
b10 E
b10 @
b11 B
b10 *
b10 0
b10 <
1+
#210000
0+
#215000
b11 "
b11 E
b11 @
b0 B
b110 D
b11 *
b11 0
b11 <
1+
#220000
0+
#225000
b110 (
b110 ?
1!
1&
b11 $
b11 A
b0 "
b0 E
b0 @
b1 B
b0 *
b0 0
b0 <
b110 =
1+
#230000
0+
#235000
b1 "
b1 E
b1 @
1!
1&
b10 B
b1 *
b1 0
b1 <
1+
#240000
0+
#245000
b10 "
b10 E
1!
b10 @
1&
b11 B
b10 *
b10 0
b10 <
1+
#250000
0+
#255000
b11 "
b11 E
1!
b11 @
1&
b0 B
b111 D
b11 *
b11 0
b11 <
1+
#260000
0+
#265000
b111 (
b111 ?
b100 $
b100 A
b0 "
b0 E
1!
b0 @
1&
b1 B
b0 *
b0 0
b0 <
b111 =
1+
#270000
0+
#275000
b1 "
b1 E
b1 @
1!
1&
b10 B
b1 *
b1 0
b1 <
1+
#280000
0+
#285000
b10 "
b10 E
1!
b10 @
1&
b11 B
b10 *
b10 0
b10 <
1+
#290000
0+
#295000
b11 "
b11 E
1!
b11 @
1&
b0 B
b1 C
b100 D
b11 *
b11 0
b11 <
1+
#300000
0+
#305000
b1 )
b1 >
b100 (
b100 ?
b1 $
b1 A
b0 "
b0 E
0!
b0 @
0&
b1 B
b0 *
b0 0
b0 <
b1 F
b100 =
1+
#310000
0+
#315000
b1 "
b1 E
b1 @
b10 B
b1 *
b1 0
b1 <
1+
#320000
0+
#325000
b10 "
b10 E
b10 @
b11 B
b10 *
b10 0
b10 <
1+
#330000
0+
#335000
b11 "
b11 E
b11 @
b0 B
b101 D
b11 *
b11 0
b11 <
1+
#340000
0+
#345000
b101 (
b101 ?
b10 $
b10 A
b0 "
b0 E
b0 @
b1 B
b0 *
b0 0
b0 <
b101 =
1+
#350000
0+
#355000
b1 "
b1 E
b1 @
b10 B
b1 *
b1 0
b1 <
1+
#360000
0+
#365000
b10 "
b10 E
b10 @
b11 B
b10 *
b10 0
b10 <
1+
#370000
0+
#375000
b11 "
b11 E
b11 @
b0 B
b110 D
b11 *
b11 0
b11 <
1+
#380000
0+
#385000
b110 (
b110 ?
1!
1&
b11 $
b11 A
b0 "
b0 E
b0 @
b1 B
b0 *
b0 0
b0 <
b110 =
1+
#390000
0+
#395000
b1 "
b1 E
b1 @
1!
1&
b10 B
b1 *
b1 0
b1 <
1+
#400000
0+
#405000
b10 "
b10 E
1!
b10 @
1&
b11 B
b10 *
b10 0
b10 <
1+
#410000
0+
#415000
b11 "
b11 E
1!
b11 @
1&
b0 B
b111 D
b11 *
b11 0
b11 <
1+
#420000
0+
#425000
b111 (
b111 ?
b100 $
b100 A
b0 "
b0 E
1!
b0 @
1&
b1 B
b0 *
b0 0
b0 <
b111 =
1+
#430000
0+
#435000
b1 "
b1 E
b1 @
1!
1&
b10 B
b1 *
b1 0
b1 <
1+
#440000
0+
#445000
b10 "
b10 E
1!
b10 @
1&
b11 B
b10 *
b10 0
b10 <
1+
#450000
0+
#455000
b11 "
b11 E
1!
b11 @
1&
b0 B
b10 C
b100 D
b11 *
b11 0
b11 <
1+
#460000
0+
#465000
b10 )
b10 >
b100 (
b100 ?
b1 $
b1 A
b0 "
b0 E
0!
b0 @
0&
b1 B
b0 *
b0 0
b0 <
b10 F
b100 =
1+
#470000
0+
#475000
b1 "
b1 E
b1 @
b10 B
b1 *
b1 0
b1 <
1+
#480000
0+
#485000
b10 "
b10 E
b10 @
b11 B
b10 *
b10 0
b10 <
1+
#490000
0+
#495000
b11 "
b11 E
b11 @
b0 B
b101 D
b11 *
b11 0
b11 <
1+
#500000
0+
#505000
b101 (
b101 ?
b10 $
b10 A
b0 "
b0 E
b0 @
b1 B
b0 *
b0 0
b0 <
b101 =
1+
#510000
0+
#515000
b1 "
b1 E
b1 @
b10 B
b1 *
b1 0
b1 <
1+
#520000
0+
#525000
b10 "
b10 E
b10 @
b11 B
b10 *
b10 0
b10 <
1+
#530000
0+
#535000
b11 "
b11 E
b11 @
b0 B
b110 D
b11 *
b11 0
b11 <
1+
#540000
0+
#545000
b110 (
b110 ?
1!
1&
b11 $
b11 A
b0 "
b0 E
b0 @
b1 B
b0 *
b0 0
b0 <
b110 =
1+
#550000
0+
#555000
b1 "
b1 E
b1 @
1!
1&
b10 B
b1 *
b1 0
b1 <
1+
#560000
0+
#565000
b10 "
b10 E
1!
b10 @
1&
b11 B
b10 *
b10 0
b10 <
1+
#570000
0+
#575000
b11 "
b11 E
1!
b11 @
1&
b0 B
b111 D
b11 *
b11 0
b11 <
1+
#580000
0+
#585000
b111 (
b111 ?
b100 $
b100 A
b0 "
b0 E
1!
b0 @
1&
b1 B
b0 *
b0 0
b0 <
b111 =
1+
#590000
0+
#595000
b1 "
b1 E
b1 @
1!
1&
b10 B
b1 *
b1 0
b1 <
1+
#600000
0+
#605000
b10 "
b10 E
1!
b10 @
1&
b11 B
b10 *
b10 0
b10 <
1+
#610000
0+
#615000
b11 "
b11 E
1!
b11 @
1&
b0 B
b11 C
b100 D
b11 *
b11 0
b11 <
1+
#620000
0+
#625000
b11 )
b11 >
b100 (
b100 ?
b1 $
b1 A
b0 "
b0 E
0!
b0 @
0&
b1 B
b0 *
b0 0
b0 <
b11 F
b100 =
1+
#630000
0+
#635000
b1 "
b1 E
b1 @
b10 B
b1 *
b1 0
b1 <
1+
#640000
0+
#645000
b10 "
b10 E
b10 @
b11 B
b10 *
b10 0
b10 <
1+
#650000
0+
#655000
b11 "
b11 E
b11 @
b0 B
b101 D
b11 *
b11 0
b11 <
1+
#660000
0+
#665000
b101 (
b101 ?
b10 $
b10 A
b0 "
b0 E
b0 @
b1 B
b0 *
b0 0
b0 <
b101 =
1+
#670000
0+
#675000
b1 "
b1 E
b1 @
b10 B
b1 *
b1 0
b1 <
1+
#680000
0+
#685000
b10 "
b10 E
b10 @
b11 B
b10 *
b10 0
b10 <
1+
#690000
0+
#695000
b11 "
b11 E
b11 @
b0 B
b110 D
b11 *
b11 0
b11 <
1+
#700000
0+
#705000
b110 (
b110 ?
1!
1&
b11 $
b11 A
b0 "
b0 E
b0 @
b1 B
b0 *
b0 0
b0 <
b110 =
1+
#710000
0+
#715000
b1 "
b1 E
b1 @
1!
1&
b10 B
b1 *
b1 0
b1 <
1+
#720000
0+
#725000
b10 "
b10 E
1!
b10 @
1&
b11 B
b10 *
b10 0
b10 <
1+
#730000
0+
#735000
b11 "
b11 E
1!
b11 @
1&
b0 B
b111 D
b11 *
b11 0
b11 <
1+
#740000
0+
#745000
b111 (
b111 ?
b100 $
b100 A
b0 "
b0 E
1!
b0 @
1&
b1 B
b0 *
b0 0
b0 <
b111 =
1+
#750000
0+
#755000
b1 "
b1 E
b1 @
1!
1&
b10 B
b1 *
b1 0
b1 <
1+
#760000
0+
#765000
b10 "
b10 E
1!
b10 @
1&
b11 B
b10 *
b10 0
b10 <
1+
#770000
0+
#775000
b11 "
b11 E
1!
b11 @
1&
b0 B
b100 C
b100 D
b11 *
b11 0
b11 <
1+
#780000
0+
#785000
b100 )
b100 >
b100 (
b100 ?
b1 $
b1 A
b0 "
b0 E
0!
b0 @
0&
b1 B
b0 *
b0 0
b0 <
b100 F
b100 =
1+
#790000
0+
#795000
b1 "
b1 E
b1 @
b10 B
b1 *
b1 0
b1 <
1+
#800000
0+
#805000
b10 "
b10 E
b10 @
b11 B
b10 *
b10 0
b10 <
1+
#810000
0+
#815000
b11 "
b11 E
b11 @
b0 B
b101 D
b11 *
b11 0
b11 <
1+
#820000
0+
#825000
b101 (
b101 ?
b10 $
b10 A
b0 "
b0 E
b0 @
b1 B
b0 *
b0 0
b0 <
b101 =
1+
#830000
0+
#835000
b1 "
b1 E
b1 @
b10 B
b1 *
b1 0
b1 <
1+
#840000
0+
#845000
b10 "
b10 E
b10 @
b11 B
b10 *
b10 0
b10 <
1+
#850000
0+
#855000
b11 "
b11 E
b11 @
b0 B
b110 D
b11 *
b11 0
b11 <
1+
#860000
0+
#865000
b110 (
b110 ?
1!
1&
b11 $
b11 A
b0 "
b0 E
b0 @
b1 B
b0 *
b0 0
b0 <
b110 =
1+
#870000
0+
#875000
b1 "
b1 E
b1 @
1!
1&
b10 B
b1 *
b1 0
b1 <
1+
#880000
0+
#885000
b10 "
b10 E
1!
b10 @
1&
b11 B
b10 *
b10 0
b10 <
1+
#890000
0+
#895000
b11 "
b11 E
1!
b11 @
1&
b0 B
b111 D
b11 *
b11 0
b11 <
1+
#900000
0+
#905000
b111 (
b111 ?
b100 $
b100 A
b0 "
b0 E
1!
b0 @
1&
b1 B
b0 *
b0 0
b0 <
b111 =
1+
#910000
0+
#915000
b1 "
b1 E
b1 @
1!
1&
b10 B
b1 *
b1 0
b1 <
1+
#920000
0+
#925000
b10 "
b10 E
1!
b10 @
1&
b11 B
b10 *
b10 0
b10 <
1+
#930000
0+
#935000
b11 "
b11 E
1!
b11 @
1&
b0 B
b101 C
b100 D
b11 *
b11 0
b11 <
1+
#940000
0+
#945000
b101 )
b101 >
b100 (
b100 ?
b1 $
b1 A
b0 "
b0 E
0!
b0 @
0&
b1 B
b0 *
b0 0
b0 <
b101 F
b100 =
1+
#950000
0+
#955000
b1 "
b1 E
b1 @
b10 B
b1 *
b1 0
b1 <
1+
#960000
0+
#965000
b10 "
b10 E
b10 @
b11 B
b10 *
b10 0
b10 <
1+
#970000
0+
#975000
b11 "
b11 E
b11 @
b0 B
b101 D
b11 *
b11 0
b11 <
1+
#980000
0+
#985000
b101 (
b101 ?
b10 $
b10 A
b0 "
b0 E
b0 @
b1 B
b0 *
b0 0
b0 <
b101 =
1+
#990000
0+
#995000
b1 "
b1 E
b1 @
b10 B
b1 *
b1 0
b1 <
1+
#1000000
0+
#1005000
b10 "
b10 E
b10 @
b11 B
b10 *
b10 0
b10 <
1+
#1010000
0+
#1015000
b11 "
b11 E
b11 @
b0 B
b110 D
b11 *
b11 0
b11 <
1+
#1020000
0+
#1025000
b110 (
b110 ?
1!
1&
b11 $
b11 A
b0 "
b0 E
b0 @
b1 B
b0 *
b0 0
b0 <
b110 =
1+
#1030000
0+
#1035000
b1 "
b1 E
b1 @
1!
1&
b10 B
b1 *
b1 0
b1 <
1+
#1040000
0+
#1045000
b10 "
b10 E
1!
b10 @
1&
b11 B
b10 *
b10 0
b10 <
1+
#1050000
0+
#1055000
b11 "
b11 E
1!
b11 @
1&
b0 B
b111 D
b11 *
b11 0
b11 <
1+
#1060000
0+
#1065000
b111 (
b111 ?
b100 $
b100 A
b0 "
b0 E
1!
b0 @
1&
b1 B
b0 *
b0 0
b0 <
b111 =
1+
#1070000
0+
#1075000
b1 "
b1 E
b1 @
1!
1&
b10 B
b1 *
b1 0
b1 <
1+
#1080000
0+
#1085000
b10 "
b10 E
1!
b10 @
1&
b11 B
b10 *
b10 0
b10 <
1+
#1090000
0+
#1095000
b11 "
b11 E
1!
b11 @
1&
b0 B
b110 C
b100 D
b11 *
b11 0
b11 <
1+
#1100000
0+
#1105000
b110 )
b110 >
b100 (
b100 ?
b1 $
b1 A
b0 "
b0 E
0!
b0 @
0&
b1 B
b0 *
b0 0
b0 <
b110 F
b100 =
1+
#1110000
0+
#1115000
b1 "
b1 E
b1 @
b10 B
b1 *
b1 0
b1 <
1+
#1120000
0+
#1125000
b10 "
b10 E
b10 @
b11 B
b10 *
b10 0
b10 <
1+
#1130000
0+
#1135000
b11 "
b11 E
b11 @
b0 B
b101 D
b11 *
b11 0
b11 <
1+
#1140000
0+
#1145000
b101 (
b101 ?
b10 $
b10 A
b0 "
b0 E
b0 @
b1 B
b0 *
b0 0
b0 <
b101 =
1+
#1150000
0+
#1155000
b1 "
b1 E
b1 @
b10 B
b1 *
b1 0
b1 <
1+
#1160000
0+
#1165000
b10 "
b10 E
b10 @
b11 B
b10 *
b10 0
b10 <
1+
#1170000
0+
#1175000
b11 "
b11 E
b11 @
b0 B
b110 D
b11 *
b11 0
b11 <
1+
#1180000
0+
#1185000
b110 (
b110 ?
1!
1&
b11 $
b11 A
b0 "
b0 E
b0 @
b1 B
b0 *
b0 0
b0 <
b110 =
1+
#1190000
0+
#1195000
b1 "
b1 E
b1 @
1!
1&
b10 B
b1 *
b1 0
b1 <
1+
#1200000
0+
#1205000
b10 "
b10 E
1!
b10 @
1&
b11 B
b10 *
b10 0
b10 <
1+
#1210000
0+
#1215000
b11 "
b11 E
1!
b11 @
1&
b0 B
b111 D
b11 *
b11 0
b11 <
1+
#1220000
0+
#1225000
b111 (
b111 ?
b100 $
b100 A
b0 "
b0 E
1!
b0 @
1&
b1 B
b0 *
b0 0
b0 <
b111 =
1+
#1230000
0+
#1235000
b1 "
b1 E
b1 @
1!
1&
b10 B
b1 *
b1 0
b1 <
1+
#1240000
0+
#1245000
b10 "
b10 E
1!
b10 @
1&
b11 B
b10 *
b10 0
b10 <
1+
#1250000
0+
#1255000
b11 "
b11 E
1!
b11 @
1&
b0 B
b111 C
b100 D
b11 *
b11 0
b11 <
1+
#1260000
0+
#1265000
b111 )
b111 >
b100 (
b100 ?
b1 $
b1 A
b0 "
b0 E
0!
b0 @
0&
b1 B
b0 *
b0 0
b0 <
b111 F
b100 =
1+
#1270000
0+
#1275000
b1 "
b1 E
b1 @
b10 B
b1 *
b1 0
b1 <
1+
#1280000
0+
#1285000
b10 "
b10 E
b10 @
b11 B
b10 *
b10 0
b10 <
1+
#1290000
0+
#1295000
b11 "
b11 E
b11 @
b0 B
b101 D
b11 *
b11 0
b11 <
1+
#1300000
0+
#1305000
b101 (
b101 ?
b10 $
b10 A
b0 "
b0 E
b0 @
b1 B
b0 *
b0 0
b0 <
b101 =
1+
#1310000
0+
#1315000
b1 "
b1 E
b1 @
b10 B
b1 *
b1 0
b1 <
1+
#1320000
0+
#1325000
b10 "
b10 E
b10 @
b11 B
b10 *
b10 0
b10 <
1+
#1330000
0+
#1335000
b11 "
b11 E
b11 @
b0 B
b110 D
b11 *
b11 0
b11 <
1+
#1340000
0+
#1345000
b110 (
b110 ?
1!
1&
b11 $
b11 A
b0 "
b0 E
b0 @
b1 B
b0 *
b0 0
b0 <
b110 =
1+
#1350000
0+
#1355000
b1 "
b1 E
b1 @
1!
1&
b10 B
b1 *
b1 0
b1 <
1+
#1360000
0+
#1365000
b10 "
b10 E
1!
b10 @
1&
b11 B
b10 *
b10 0
b10 <
1+
#1370000
0+
#1375000
b11 "
b11 E
1!
b11 @
1&
b0 B
b111 D
b11 *
b11 0
b11 <
1+
#1380000
0+
#1385000
b111 (
b111 ?
b100 $
b100 A
b0 "
b0 E
1!
b0 @
1&
b1 B
b0 *
b0 0
b0 <
b111 =
1+
#1390000
0+
#1395000
b1 "
b1 E
b1 @
1!
1&
b10 B
b1 *
b1 0
b1 <
1+
#1400000
0+
#1405000
b10 "
b10 E
1!
b10 @
1&
b11 B
b10 *
b10 0
b10 <
1+
#1410000
0+
#1415000
b11 "
b11 E
1!
b11 @
1&
b0 B
b1000 C
b100 D
b11 *
b11 0
b11 <
1+
#1420000
0+
#1425000
b1000 )
b1000 >
b100 (
b100 ?
b1 $
b1 A
b0 "
b0 E
0!
b0 @
0&
b1 B
b0 *
b0 0
b0 <
b1000 F
b100 =
1+
#1430000
0+
#1435000
b1 "
b1 E
b1 @
b10 B
b1 *
b1 0
b1 <
1+
#1440000
0+
#1445000
b10 "
b10 E
b10 @
b11 B
b10 *
b10 0
b10 <
1+
#1450000
0+
#1455000
b11 "
b11 E
b11 @
b0 B
b101 D
b11 *
b11 0
b11 <
1+
#1460000
0+
#1465000
b101 (
b101 ?
b10 $
b10 A
b0 "
b0 E
b0 @
b1 B
b0 *
b0 0
b0 <
b101 =
1+
#1470000
0+
#1475000
b1 "
b1 E
b1 @
b10 B
b1 *
b1 0
b1 <
1+
#1480000
0+
